{"name":"Boxdialog","tagline":"一款想到即能做到的通用弹窗组件","body":"# boxDialog\r\nboxDialog 是一款轻量级的弹窗通用组件，包括弹出字符串内容、自定义 DOM 结构、iframe 页面等以及快捷操作等功能，具有高度的可定制性。\r\n\r\n\r\n### 1. 基本使用方法：\r\n调用主函数 `boxDialog.open()`, 传入相关参数.\r\n\r\n```js\r\n  boxDialog.open({\r\n\t  content: '（成功）success',\r\n\t  icon:'success'\t\r\n  \t});\r\n```\r\n\r\n### 2. 弹出自定义 DOM 结构:\r\n\r\n```js\r\n    boxDialog.open({\r\n\t\tcontent: document.getElementById('demo_dom_content'),   // or jQuery： $('#demo_dom_content')[0]\r\n\t\tsize:['400px']\r\n\t});\r\n```\r\n##### 注意：size参数为弹窗的宽高，如：size:['400px','300px']，只设置一个为宽度。支持 px 和 % 两种单位。\r\n\r\n### 3. 弹出 iframe 页面:\r\n```js\r\n      boxDialog.open({\r\n\t\ttitle: '弹出了一个 iframe 嵌套页面',\r\n\t\tcontent: {\r\n\t\t\tiframe: true,\r\n\t\t\turl: 'demo_iframe.html'\r\n\t\t},\r\n\t\tsize:['400px','200px']\r\n\t});\r\n```\r\n\r\n### 4. 可使用的 boxDialog 参数：\r\n\r\n```js\r\n//可使用的参数\r\nconfigs = {\r\n\ttitle: '\\u6d88\\u606f',\t\t       // 标题，默认'消息'.\r\n\tcontent: '欢迎使用boxDialog!',     // 弹窗主内容.\r\n\tok: true,\t\t\t\t\t       // 是否显示确定按钮，默认显示.\r\n\tcancel: true,\t\t\t\t       // 是否显示取消按钮，默认显示.\r\n\tokText: '\\u786e\\u5b9a',\t\t       // 确定按钮文本，默认为：确定. \r\n\tcancelText: '\\u53d6\\u6d88',\t       // 取消按钮文本, 默认为：取消.\r\n\tsize: ['auto','auto'],             // 内容宽，高, 默认auto.\r\n\tpadding: '20px',\t\t           // 内容与边界填充padding,格式css语法.\r\n\ticon: null,\t\t\t\t\t       // 图标名称,字符串,如: icon:'success'.\r\n\ttime: null,\t\t\t\t\t       // 自动关闭时间，单位秒.\r\n\tshade: {\t\t\t\t\t\t   // 遮罩层默认显示，设置shade:false, 不显示遮罩.\r\n\t\tbackground: '#000',\t\t\t   // 遮罩层背景色，默认黑色.\r\n\t\topacity: 0.8,                  // 遮罩层透明度, 默认0.8.\r\n\t\tduration: 200                  // 遮罩层动画速度, 单位毫秒，默认200.\r\n\t},\t\t\t\t       \r\n\tfixed: true,\t\t\t\t       // 是否固定位置，默认true固定位置.\r\n\tzIndex: 2010,\t\t\t\t       // 弹窗的堆叠顺序.\r\n\tdrag: false,\t\t\t\t       // 拖拽开关，默认关闭.\r\n\tesc: true,\t\t\t\t\t       // 是否支持Esc键关闭.\r\n\tposition: null,\t       \t           // X,Y轴坐标,不设置默认居中，设置如：{left:'100px',top:'100px'}.\r\n\tcloseBtn: true,                    // 弹窗的关闭按钮是否显示，默认显示.\r\n\tvarBtns: null,\t\t\t\t   \t   // 自定义按钮, 格式如:[{text:'按钮3',className:null,callback:null},{text:'按钮4',className:null,callback:null}].\r\n\tclassName: null,\t\t\t\t   // {string}     自定义弹窗最外层class.\r\n\tinitCallback: null,\t\t\t       // {function}   初始化成功执行的回调函数.\r\n\tokCallback: null,\t\t\t\t   // {function}   点击确定按钮执行的回调函数.\r\n\tcancelCallback: null,\t\t\t   // {function}   点击取消按钮执行的回调函数.\r\n\tcloseCallback: null\t\t\t       // {function}   弹窗关闭执行的回调函数.\r\n};\r\n```\r\n#### 注意：以上是可设置的参数，可根据自己需求灵活运用。\r\n\r\n#### 回调函数使用：\r\nokCallback, cancelCallback, initCallback, closeCallback 用于不同场景下的回调函数， 参数分别为点击确定按钮、点击取消按钮、弹窗初始化成功后和关闭弹窗（如：2秒后自动关闭）执行的回调函数，可以在回调函数中执行ajax等操作DOM，\r\n回调函数中可用 this 关键字，指向弹窗实体，可调用内部方法。\r\n\r\n#### 回调函数接受一个参数返回弹窗索引，如：\r\n```js\r\nokCallback: function(index){\r\n\t\t\t\t//index就是该弹窗索引\r\n\t\t\t}\r\n\r\n```\r\n\r\n\r\n### 5. 外部可用方法:\r\n\r\n```js\r\nopen: dialog,\r\nclose: close,\r\ncloseAll: closeAll,\r\nmsg: msg,\r\nalert: alert\r\n```\r\n\r\n##### open: dialog\t主方法，即弹出窗口实体，使用方法：boxDialog.open(), 传入参数;\r\n##### close: close\t接受一个index参数，关闭指定索引的弹窗，使用方法：boxDialog.close(2), 表示关闭索引为 2 的弹窗；若不传参数默认关闭最上层的弹窗;\r\n##### closeAll: closeAll\t关闭页面中所有弹窗，使用方法：boxDialog.closeAll();\r\n##### msg: msg\t弹出快捷信息提示，使用方法：boxDialog.msg(title,content,icon,sec), 参数都可选; 如：boxDialog.msg( '提交成功','提交成功 1s 后消失','success',1 );\r\n##### alert: alert 模拟原生的alert效果，使用方法：boxDialog.alert(content,callback,w), 参数都可选; 如: boxDialog.alert('提交成功');\r\n\r\n\r\n### 6. 模块化使用boxDialog, 以 seajs 为例:\r\n#### 假如调用页面是 index.html, 包含以下代码：\r\n```js\r\nseajs.config({\r\n        base: './js/',\r\n        alias: {\r\n          'jquery': 'modules/jquery-1.9.1.min',\r\n          'boxDialog':'../../lib/dist/boxDialog'\r\n      \t}\r\n    });\r\nseajs.use(['jquery', 'modules/main'], function($,ex){\r\n\t$('#abc').on('click', function(){\r\n\t\tex.boxDialog.alert('abc');\r\n\t});\r\n});\r\n```\r\n#### main.js 是调用的模块, 包含以下代码：\r\n```js\r\ndefine(function(require,exports,module){\r\n\tvar boxDialog = require('boxDialog');\r\n\texports.boxDialog = boxDialog;\r\n})\r\n```\r\n#### 以上代码可正确使用 boxDialog 弹窗组件.\r\n\r\n## 结语：\r\nboxDialog 已成功被多家公司使用以及某大型上市公司的多套系统、网站都在使用。 boxDialog 将持续更新，优化其性能和体验，谢谢关注。\r\n\r\n## Release History\r\nV1.0\r\n\r\n## License\r\nCopyright (c) 2015 xia bing, @Blog:http://ddbing.com/. Licensed under the MIT license.\r\n","google":"binson","note":"Don't delete this file! It's used internally to help with page regeneration."}